api/__init__.py
api/project_api.py
cli/__init__.py
cli/__main__.py
cli/check.py
cli/config.py
cli/init.py
cli/project.py
cli/submit.py
cli/ui/__init__.py
cli/ui/console.py
cli/wake.py
config/__init__.py
config/config.py
wake_versions/__init__.py
wake_versions/exceptions.py
wake_versions/manager.py
wake_versions/resources/conda_public_key.pem
wake_arena_cli-1.4.0.dist-info/METADATA
wake_arena_cli-1.4.0.dist-info/WHEEL
wake_arena_cli-1.4.0.dist-info/entry_points.txt
wake_arena_cli-1.4.0.dist-info/RECORD
