Metadata-Version: 2.3
Name: wake-arena-cli
Version: 1.4.0
Summary: Wake Arena CLI tool
Author: Pavel Švagr
Author-email: pavel.svagr@ackee.cz
Requires-Python: >=3.8, !=2.7.*, !=3.0.*, !=3.1.*, !=3.2.*, !=3.3.*, !=3.4.*, !=3.5.*, !=3.6.*, !=3.7.*
Classifier: Programming Language :: Python :: 3
Classifier: Programming Language :: Python :: 3.10
Classifier: Programming Language :: Python :: 3.11
Classifier: Programming Language :: Python :: 3.12
Classifier: Programming Language :: Python :: 3.13
Requires-Dist: cryptography (>=44.0.0,<45.0.0)
Requires-Dist: google-cloud-storage (>=2.19.0,<3.0.0)
Requires-Dist: inquirer (>=3.4.0,<4.0.0)
Requires-Dist: packaging (>=24,<25)
Requires-Dist: python-dateutil (>=2,<3)
Requires-Dist: pyyaml (>=6.0.2,<7.0.0)
Requires-Dist: requests (>=2.32.3,<3.0.0)
Requires-Dist: requests-toolbelt (>=1.0.0,<2.0.0)
Requires-Dist: rich (>=13.8.1,<14.0.0)
Requires-Dist: rich-click (>=1.8.3,<2.0.0)
Requires-Dist: schema (>=0.7.7,<0.8.0)
Requires-Dist: typing-extensions (>=4,<5)
